rajkushw/__init__.py
rajkushw/rajkushw.py
rajkushw/test.py
rajkushw-1.0.dist-info/METADATA
rajkushw-1.0.dist-info/WHEEL
rajkushw-1.0.dist-info/top_level.txt
rajkushw-1.0.dist-info/RECORD
