Metadata-Version: 2.1
Name: rajkushw
Version: 1.0
Summary: test rajkushw package
Home-page: UNKNOWN
Author: UNKNOWN
Author-email: UNKNOWN
License: UNKNOWN
Platform: UNKNOWN
